[
  {
   "name": "Cassandre",
   "slug": "cassandre",
   "image": "https://drive.google.com/uc?export=view&id=1J-vz6TcQLMN7q7-mljzIqQlab9bxQyPT"
  },
  {
   "name": "Evolia",
   "slug": "evolia",
   "image": "https://drive.google.com/uc?export=view&id=1E5IVmcmAx3z_fOKuogw-fbezJiVfmwFb"
  },
  {
   "name": "Hampton",
   "slug": "hampton",
   "image": "https://drive.google.com/uc?export=view&id=1LJpkY0ZU4gpFlTk1ICeczbMIXKj5qVpO"
  },
  {
   "name": "Jaya",
   "slug": "jaya",
   "image": "https://drive.google.com/uc?export=view&id=155e_AFMLJHxkOmob2R1XVcnqCmY2eflp"
  },
  {
   "name": "Kreypiak",
   "slug": "kreypiak",
   "image": "https://drive.google.com/uc?export=view&id=1O-yj5yPxRql2nPD2xSbZSzruuOQe5bKy"
  },
  {
   "name": "Kuta",
   "slug": "kuta",
   "image": "https://drive.google.com/uc?export=view&id=1dsEw2phCEXxjhDnOcdOso9I5E0Fthg_n"
  },
  {
   "name": "Mikha",
   "slug": "mikha",
   "image": "https://drive.google.com/uc?export=view&id=1M4zt4zJiOq9--I14h7jt6xKeQB7yz8La"
  },
  {
   "name": "Minimalis",
   "slug": "minimalis",
   "image": "https://drive.google.com/uc?export=view&id=1VOT5EJBx7hdbb61VB2QpO7PBKVp5V0nG"
  },
  {
   "name": "Oasis",
   "slug": "oasis",
   "image": "https://drive.google.com/uc?export=view&id=1fk_Z6ZFaQ0k9NvyS6dJ3TatEBb8THtsI"
  },
  {
   "name": "Olanda",
   "slug": "olanda",
   "image": "https://drive.google.com/uc?export=view&id=1_tSQy_dfBosdFssjOlCKoO1LWmzBBvtu"
  },
  {
   "name": "Sherry",
   "slug": "sherry",
   "image": "https://drive.google.com/uc?export=view&id=1jo71jvIBfjHUsycM2s-jdBUu5VTPEp-r"
  },
  {
   "name": "Slats",
   "slug": "slats",
   "image": "https://drive.google.com/uc?export=view&id=1TKoCAAyU4hTrdg9kAsm7h_CCWhJ5Cr-P"
  },
  {
   "name": "Ubud",
   "slug": "ubud",
   "image": "https://drive.google.com/uc?export=view&id=1sfXxnD4HMkr_BSK-Zssk1leiuTP6Zjbt"
  },
  {
   "name": "Coiffeuse",
   "slug": "coiffeuse",
   "image": "https://drive.google.com/uc?export=view&id=1OkZXtpOGiXc92yf2uqIs6MoC3npxDy_O"
  }
 ]