[
  {
   "Finitions": "Miel",
   "Image": "https:\/\/drive.google.com\/file\/d\/1-kgK81hzW6aqh0-98zDTZTxjH2XXGmGe\/view?usp=sharing"
  },
  {
   "Finitions": "Cérusé Blanc",
   "Image": "https:\/\/drive.google.com\/file\/d\/1EWxemRH1lrI9AfkE-vi-FR9PXUgHJA2N\/view?usp=sharing"
  },
  {
   "Finitions": "Brut",
   "Image": "https:\/\/drive.google.com\/file\/d\/1qTWkkn7hLHwqWBII3tRhhyPKzPYcolgj\/view?usp=sharing"
  },
  {
   "Finitions": "Cérusé Noir",
   "Image": "https:\/\/drive.google.com\/file\/d\/1tOLncc0-h3mjV_1ECdTJMrPVTAwaiJ3u\/view?usp=sharing"
  }
 ]